{
    "data": {
        "business_id": "0x47dec26be15494fd:0x92f3b74b723127f1",
        "phone_number": "+441303874848",
        "name": "Beach 48",
        "full_address": "Beach 48, 48 High St, Dymchurch, Romney Marsh TN29 0NL, United Kingdom",
        "latitude": 51.0247165,
        "longitude": 0.9959446,
        "review_count": 653,
        "rating": 4.5,
        "timezone": "Europe/London",
        "website": "beach48.co.uk",
        "website_full": "http://www.beach48.co.uk/",
        "place_id": "ChIJ_ZRU4WvC3kcR8Scxcku385I",
        "place_link": "https://www.google.com/maps/place/data=!3m1!4b1!4m2!3m1!1s0x47dec26be15494fd:0x92f3b74b723127f1",
        "types": [
            "Fish & chips restaurant",
            "Fast food restaurant"
        ],
        "price_level": "£10–20",
        "working_hours": [],
        "is_permanently_closed": false,
        "is_temporarily_closed": false,
        "state": null,
        "photos": [
            {
                "url": "https://lh3.googleusercontent.com/gps-cs-s/AG0ilSwM_t4gyvs4qFRaeokRizdJKopKT_q5t4hcWOpUAmUtpd8k64MDghUMmFF16AZvZYvrGr6jbqPAd_P_MN1GDSWtRgUsf7vsw0Qkvw8_jgyScpytUVxd8cZ7vasf1HzOjDDQBsdEMQ=w224-h298-k-no",
                "description": "All"
            },
            {
                "url": "https://lh3.googleusercontent.com/gps-cs-s/AG0ilSyg8ahxSB2x7SHi2XDJXV-71GONPhXkMn0DAbDnb43o0Cn3OO3jm4Z17w5IfNITruM-fzKDPMsdOaWokcVDcHjRvUSkwWm3lBLUDUWA6NG4TJa4oiK3beDtS4xNKxgKPz_uxPD8Z4NdvS10=w367-h298-k-no",
                "description": "Latest"
            },
            {
                "url": "https://lh3.googleusercontent.com/gps-cs-s/AG0ilSz0tlrGe-X88FhGAR3qP79PnkQYFl9WfG5kjCgkbrXnTlIouwre125EIgM9iOCffIYKp1JuYpfI5ZR-aWTleP1E3fIGxCHkDWJWUy4r5iQend3lorZd2tO04XPVUizsdQFgvSi5EQ=w224-h298-k-no",
                "description": "Menu"
            },
            {
                "url": "https://lh3.googleusercontent.com/gps-cs-s/AG0ilSwywsTa4IodK3sP-UxUXDCnoUtb-lNNASWCu6BcJSjXeOcBFRBVnLwh64A152ebJExaUVyLcgz3xB7Hi392a1_Y3CVzyOu6mzjvsknAEbFw-63uXJLSvDW6sXkZ5_57GqyArsSXtQ=w397-h298-k-no",
                "description": "Food & drink"
            },
            {
                "url": "https://lh3.googleusercontent.com/gps-cs-s/AG0ilSws5pNvwzk-wZVO1_XYcukqWOURnuwUVuSGsl2DtcA3A3EIULM5IAGLKMVteSeHskesZfnUBKcOUhdfU17uDZQtbzblpUcXPA6FWWcEYOszzb92WhR3Qhk18cCrqtTSpBsf7tKTpw=w397-h298-k-no",
                "description": "Vibe"
            },
            {
                "url": "https://lh3.googleusercontent.com/gps-cs-s/AG0ilSxI_2en5OnCYnGj420W24yHbO-buvT-Qa2JWw9odTK0a1RLDap4bh7mxz1qI93xE4cgtztrmdbdLZHpeeQ4iUno7D4_TksbDjL5B6u6cQh27gzsFBr_3jRGNTaDbBQka9Uqq4n0=w372-h298-k-no",
                "description": "Fish and chips"
            },
            {
                "url": "https://lh3.googleusercontent.com/gps-cs-s/AG0ilSz6SLTjt1sDOTpuv3pu0wMulP0hhWAgRGxboKfY0XwRV0-z-30AdWXWCxuZDEICRaXV6OWUkfp2MvYrxJmiWRAgwu39ts-Csp9fx6OHxQPCWcdhIK1Dxo_mPJKFoolcFLkmhk5RFOryxONQ=w397-h298-k-no",
                "description": "French fries"
            },
            {
                "url": "https://streetviewpixels-pa.googleapis.com/v1/thumbnail?panoid=SQ94i5yg3lfRfM90BUTMKA&cb_client=maps_sv.tactile.gps&w=224&h=298&yaw=326.64145&pitch=0&thumbfov=100",
                "description": "Street View & 360°"
            }
        ],
        "description": [],
        "reviews": [
            {
                "user_name": "chloe hobbs",
                "user_total_reviews": 12,
                "user_total_photos": 5,
                "user_avatar": "https://lh3.googleusercontent.com/a-/ALV-UjVIzQRcNg9CwKueTfRCMMcTtuUS32VzAkiZvaEq71EqoKx6oIrz=s120-c-rp-mo-br100",
                "user_link": "https://www.google.com/maps/contrib/113193313166878187699?hl=en",
                "iso_date": "2025-06-19 00:55:50",
                "iso_date_timestamp": 1750294550024742,
                "iso_date_of_last_edit": "2025-06-19 00:55:50",
                "iso_date_of_last_edit_timestamp": 1750294550024742,
                "review_id": "Ci9DQUlRQUNvZENodHljRjlvT25sc2NXcGZWbTVKZDJSemEyTjNNa3RFWjBGb1VFRRAB",
                "review_time": "4 months ago",
                "review_timestamp": 1750294550024742,
                "review_link": "https://www.google.com/maps/reviews/data=!4m8!14m7!1m6!2m5!1sCi9DQUlRQUNvZENodHljRjlvT25sc2NXcGZWbTVKZDJSemEyTjNNa3RFWjBGb1VFRRAB!2m1!1s0x0:0x92f3b74b723127f1!3m1!1s2@1:CAIQACodChtycF9oOnlscWpfVm5Jd2Rza2N3MktEZ0FoUEE%7C0cJq-L0TNgS%7C?hl=en",
                "review_text": null,
                "review_photos": [],
                "business_response_text": null,
                "review_services": {
                    "Food": 5,
                    "Service": 1,
                    "Atmosphere": 1
                },
                "translations": [],
                "review_rate": 1,
                "review_cursor": "CAESY0NBRVFGUnBFUTJwRlNVRlNTWEJEWjI5QlVEY3RjR1ZIZEV3NVgxOWZSV2hEVUhWUlIwaEpiRUZXZFhSVFRVMW1WVUZCUVVGQlIyZHVPUzB4TkVOaFNIQlJjV1pqV1VGRFNVRQ=="
            },
            {
                "user_name": "Kim Hazeldine",
                "user_total_reviews": 162,
                "user_total_photos": 244,
                "user_avatar": "https://lh3.googleusercontent.com/a-/ALV-UjUhEeobIy2ekqdQHbPrCicOMfSLoOB9APAsIoj-XVkJieX4-q4Iyw=s120-c-rp-mo-ba5-br100",
                "user_link": "https://www.google.com/maps/contrib/106881443998353096458?hl=en",
                "iso_date": "2021-04-01 06:16:02",
                "iso_date_timestamp": 1617257762426364,
                "iso_date_of_last_edit": "2021-04-01 06:16:32",
                "iso_date_of_last_edit_timestamp": 1617257792059671,
                "review_id": "ChdDSUhNMG9nS0VJQ0FnSUNLaXRPLWxBRRAB",
                "review_time": "4 years ago",
                "review_timestamp": 1617257792059671,
                "review_link": "https://www.google.com/maps/reviews/data=!4m8!14m7!1m6!2m5!1sChdDSUhNMG9nS0VJQ0FnSUNLaXRPLWxBRRAB!2m1!1s0x0:0x92f3b74b723127f1!3m1!1s2@1:CIHM0ogKEICAgICKitO-lAE%7CCgsIwMqVgwYQ2IO6HA%7C?hl=en",
                "review_text": null,
                "review_photos": [],
                "business_response_text": null,
                "review_services": [],
                "translations": [],
                "review_rate": 1,
                "review_cursor": "CAESYENBRVFGaHBDUTJrNFNVRlNTVzVEWjI5QlVEY3RjR1pmWDE5ZlgxOWZSV2hDYkUxdWNVOHdNRkpTZW0xUWNWRkJiMEZCUVVGQlIyZG1YMEZ2WkhvM1NETkZSMEZCYVVGQg=="
            },
            {
                "user_name": "Michael Titmuss",
                "user_total_reviews": 3,
                "user_total_photos": 0,
                "user_avatar": "https://lh3.googleusercontent.com/a-/ALV-UjViKvTXZrdzDOEhJvt5q5c9gfv-wS1_Pft28kTXLXiaGm6jjCg=s120-c-rp-mo-ba3-br100",
                "user_link": "https://www.google.com/maps/contrib/116358025960724325965?hl=en",
                "iso_date": "2019-10-19 23:08:29",
                "iso_date_timestamp": 1571526509210738,
                "iso_date_of_last_edit": "2019-10-19 23:08:29",
                "iso_date_of_last_edit_timestamp": 1571526509210738,
                "review_id": "ChdDSUhNMG9nS0VJQ0FnSUQwaUlDVnJ3RRAB",
                "review_time": "6 years ago",
                "review_timestamp": 1571526509210738,
                "review_link": "https://www.google.com/maps/reviews/data=!4m8!14m7!1m6!2m5!1sChdDSUhNMG9nS0VJQ0FnSUQwaUlDVnJ3RRAB!2m1!1s0x0:0x92f3b74b723127f1!3m1!1s2@1:CIHM0ogKEICAgID0iICVrwE%7CCgsI7a6u7QUQ0La-ZA%7C?hl=en",
                "review_text": null,
                "review_photos": [],
                "business_response_text": null,
                "review_services": [],
                "translations": [],
                "review_rate": 1,
                "review_cursor": "CAESYENBRVFGeHBDUTJrNFNVRlNTVzVEWjI5QlVEY3RjR1pmWDE5ZlgxOWZSV2hCZURKc1FraHlXbEJhYmxkVE0ySkNiMEZCUVVGQlIyZG1YMEZ3U1ZwMVNERnNSMEZCYVVGQg=="
            },
            {
                "user_name": "Andrew Mannering",
                "user_total_reviews": 3,
                "user_total_photos": 0,
                "user_avatar": "https://lh3.googleusercontent.com/a/ACg8ocJdga6WsTeWMwMhpERwOaFg7vQupKZDblZfQ8ejd52uYf9www=s120-c-rp-mo-br100",
                "user_link": "https://www.google.com/maps/contrib/107880257205869154357?hl=en",
                "iso_date": "2018-12-12 17:56:31",
                "iso_date_timestamp": 1544637390599965,
                "iso_date_of_last_edit": "2018-12-12 17:56:31",
                "iso_date_of_last_edit_timestamp": 1544637390599965,
                "review_id": "ChdDSUhNMG9nS0VJQ0FnSUNJal9UUTZRRRAB",
                "review_time": "6 years ago",
                "review_timestamp": 1544637390599965,
                "review_link": "https://www.google.com/maps/reviews/data=!4m8!14m7!1m6!2m5!1sChdDSUhNMG9nS0VJQ0FnSUNJal9UUTZRRRAB!2m1!1s0x0:0x92f3b74b723127f1!3m1!1s2@1:CIHM0ogKEICAgICIj_TQ6QE%7CCgwIzpfF4AUQ4v6KngI%7C?hl=en",
                "review_text": null,
                "review_photos": [],
                "business_response_text": null,
                "review_services": [],
                "translations": [],
                "review_rate": 1,
                "review_cursor": "CAESYENBRVFHQnBDUTJrNFNVRlNTVzVEWjI5QlVEY3RjR1pmWDE5ZlgxOWZSV2hFTTFsVE5GWjVNSGx1T1ZkTmNYbE9RVUZCUVVGQlIyZG1YMEZ3YUdOaUxVUTBSMEZCYVVGQg=="
            },
            {
                "user_name": "hannah spencer",
                "user_total_reviews": 48,
                "user_total_photos": 60,
                "user_avatar": "https://lh3.googleusercontent.com/a-/ALV-UjWszaQq7ViYYr_DAiu90w8dFtV3yBg7R18l8c5MTRFFJShWHIvD=s120-c-rp-mo-ba3-br100",
                "user_link": "https://www.google.com/maps/contrib/117478399745687619059?hl=en",
                "iso_date": "2020-02-05 14:41:17",
                "iso_date_timestamp": 1580913676713838,
                "iso_date_of_last_edit": "2023-07-29 00:01:44",
                "iso_date_of_last_edit_timestamp": 1690588904017605,
                "review_id": "ChdDSUhNMG9nS0VJQ0FnSUNzc1k2NDZnRRAB",
                "review_time": "Edited 2 years ago",
                "review_timestamp": 1690588904017605,
                "review_link": "https://www.google.com/maps/reviews/data=!4m8!14m7!1m6!2m5!1sChdDSUhNMG9nS0VJQ0FnSUNzc1k2NDZnRRAB!2m1!1s0x0:0x92f3b74b723127f1!3m1!1s2@1:CIHM0ogKEICAgICssY646gE%7CCgsI6K2RpgYQiMOyCA%7C?hl=en",
                "review_text": "Alot has changed in 3 years,gone down hill big time , 3 years ago I had the special which was cod, chips, salad, mashy pies, cake and custard and a hot drink all for £7 each and was delicious . Couldn't rate them any higher.\nNow just the chips and the fish is £10.50 .cake £3,Drink around the same.\nChips are horrible ,dry and tasteless.\nSmall fish,hardly any batter. Served on paper which you and up slicing into.\nYou no longer get salad or peas as a side.\nService is slow yet plenty of staff. We ordered drinks and ended up having to wait while 2 tables who order after us got their tea before we got our cappuccinos. Which was mainly milk and Luke warm and the girl who served us was lovely but her long 2 inche nails where all over my plate and coffee cup which she spilt as cants hold things with the nails.\nStaff are all friendly and nice. But it's the food and price thats lost my original high rating.",
                "review_photos": [
                    "https://lh3.googleusercontent.com/geougc-cs/AMBA38u-VpOoAqv8p6qACqXRVMk82qvX34cjw_BhRhE7kNghfDe_3yWTmyYjJiybBt4gomiL6R5_rf9hgI_r-xY9YXSw7OFvY9uRdhZRqu4axacIG43fb6qJ8iL3xkzXeVlWQEQRJbo1yg"
                ],
                "business_response_text": null,
                "review_services": {
                    "Service": 2,
                    "Meal type": "Lunch",
                    "Price per person": "£10–20",
                    "Food": 2,
                    "Atmosphere": 3
                },
                "translations": {
                    "en": "Alot has changed in 3 years,gone down hill big time , 3 years ago I had the special which was cod, chips, salad, mashy pies, cake and custard and a hot drink all for £7 each and was delicious . Couldn't rate them any higher.\nNow just the chips and the fish is £10.50 .cake £3,Drink around the same.\nChips are horrible ,dry and tasteless.\nSmall fish,hardly any batter. Served on paper which you and up slicing into.\nYou no longer get salad or peas as a side.\nService is slow yet plenty of staff. We ordered drinks and ended up having to wait while 2 tables who order after us got their tea before we got our cappuccinos. Which was mainly milk and Luke warm and the girl who served us was lovely but her long 2 inche nails where all over my plate and coffee cup which she spilt as cants hold things with the nails.\nStaff are all friendly and nice. But it's the food and price thats lost my original high rating."
                },
                "review_rate": 2,
                "review_cursor": "CAESY0NBRVFHUnBFUTJwRlNVRlNTWEJEWjI5QlVEY3RjbmRYT0ZoMlgxOWZSV2hDVFRCd2VYaFFMVlJMWkhKUVEyRkRWVUZCUVVGQlIyZHVPVEpqT0VOa2JVVk5hR0UwV1VGRFNVRQ=="
            },
            {
                "user_name": "Alex Miles",
                "user_total_reviews": 2,
                "user_total_photos": 0,
                "user_avatar": "https://lh3.googleusercontent.com/a-/ALV-UjWOZ7I74x7i2yLLXAe9JHS5uc4xqr6qbB1k_GHpmpzSfWtWsrY=s120-c-rp-mo-br100",
                "user_link": "https://www.google.com/maps/contrib/108249700351343733189?hl=en",
                "iso_date": "2023-04-05 17:09:35",
                "iso_date_timestamp": 1680714574880474,
                "iso_date_of_last_edit": "2023-04-05 17:09:35",
                "iso_date_of_last_edit_timestamp": 1680714574880474,
                "review_id": "ChZDSUhNMG9nS0VJQ0FnSUNSMmVLOEVnEAE",
                "review_time": "2 years ago",
                "review_timestamp": 1680714574880474,
                "review_link": "https://www.google.com/maps/reviews/data=!4m8!14m7!1m6!2m5!1sChZDSUhNMG9nS0VJQ0FnSUNSMmVLOEVnEAE!2m1!1s0x0:0x92f3b74b723127f1!3m1!1s2@1:CIHM0ogKEICAgICR2eK8Eg%7CCgwIzta2oQYQkO_rowM%7C?hl=en",
                "review_text": "Sorry but this has gone down hill.  Chips were ok but very mushy and stuck together.  The fish cake was like some cheap Iceland budget choice and the sausage had me on the toilet 2 hours later, you can’t even call it a.sausage it had pink bits in it and probably no more than 20%  meat.  If this is your business you should provide quality food as you certainly pay a lot for substandard grub in my mind.",
                "review_photos": [],
                "business_response_text": null,
                "review_services": {
                    "Service": "Take out",
                    "Meal type": "Lunch",
                    "Price per person": "£1–10"
                },
                "translations": {
                    "en": "Sorry but this has gone down hill.  Chips were ok but very mushy and stuck together.  The fish cake was like some cheap Iceland budget choice and the sausage had me on the toilet 2 hours later, you can’t even call it a.sausage it had pink bits in it and probably no more than 20%  meat.  If this is your business you should provide quality food as you certainly pay a lot for substandard grub in my mind."
                },
                "review_rate": 2,
                "review_cursor": "CAESY0NBRVFHaHBFUTJwRlNVRlNTWEJEWjI5QlVEY3Rjbmd0YVZSZlgxOWZSV2hETjBrMk1HeHhkSFZ0WkRsR1MzSlVXVUZCUVVGQlIyZHVPVE5qVFVObFN6SmhNRGs0V1VGRFNVRQ=="
            },
            {
                "user_name": "simone david",
                "user_total_reviews": 108,
                "user_total_photos": 6,
                "user_avatar": "https://lh3.googleusercontent.com/a-/ALV-UjV5JsTKEFtboD7joLm-C3VfmKR9QVfg8QTfLHmEr3RX0sX0fshQzA=s120-c-rp-mo-ba4-br100",
                "user_link": "https://www.google.com/maps/contrib/101006955732275983976?hl=en",
                "iso_date": "2018-05-12 14:13:04",
                "iso_date_timestamp": 1526134383669000,
                "iso_date_of_last_edit": "2018-05-12 14:13:04",
                "iso_date_of_last_edit_timestamp": 1526134383669000,
                "review_id": "ChdDSUhNMG9nS0VJQ0FnSUN3OTdfNHhBRRAB",
                "review_time": "7 years ago",
                "review_timestamp": 1526134383669000,
                "review_link": "https://www.google.com/maps/reviews/data=!4m8!14m7!1m6!2m5!1sChdDSUhNMG9nS0VJQ0FnSUN3OTdfNHhBRRAB!2m1!1s0x0:0x92f3b74b723127f1!3m1!1s2@1:CIHM0ogKEICAgICw97_4xAE%7CCgwI7-zb1wUQwMKAvwI%7C?hl=en",
                "review_text": "Good is tasty.  Fish is fresh. Service is very slow.  Waitresses had to be  signalled over before they came over to our table.  Had to catch another waitress' eye before I could get more condiments!!!  As a tourist, I was unimpressed.!!",
                "review_photos": [],
                "business_response_text": null,
                "review_services": [],
                "translations": {
                    "en": "Good is tasty.  Fish is fresh. Service is very slow.  Waitresses had to be  signalled over before they came over to our table.  Had to catch another waitress' eye before I could get more condiments!!!  As a tourist, I was unimpressed.!!"
                },
                "review_rate": 2,
                "review_cursor": "CAESY0NBRVFHeHBFUTJwRlNVRlNTWEJEWjI5QlVEY3RjbmxIYVhsMlgxOWZSV2hDY1hoVWQweHFTV0kxZFZKdVkwdHZPRUZCUVVGQlIyZHVPVE5vUlVOdVMzUk9Wemh2V1VGRFNVRQ=="
            },
            {
                "user_name": "Michał Rastecki",
                "user_total_reviews": 98,
                "user_total_photos": 3,
                "user_avatar": "https://lh3.googleusercontent.com/a/ACg8ocLEwuoH8hm0itu7KebBfAEFM5DoUAJkKeNEfy2YGOP63PjdQg=s120-c-rp-mo-ba4-br100",
                "user_link": "https://www.google.com/maps/contrib/117418743567415385443?hl=en",
                "iso_date": "2023-05-02 07:59:36",
                "iso_date_timestamp": 1683014375982797,
                "iso_date_of_last_edit": "2023-05-02 08:01:34",
                "iso_date_of_last_edit_timestamp": 1683014493993891,
                "review_id": "ChZDSUhNMG9nS0VJQ0FnSURSX2V2SkFREAE",
                "review_time": "2 years ago",
                "review_timestamp": 1683014493993891,
                "review_link": "https://www.google.com/maps/reviews/data=!4m8!14m7!1m6!2m5!1sChZDSUhNMG9nS0VJQ0FnSURSX2V2SkFREAE!2m1!1s0x0:0x92f3b74b723127f1!3m1!1s2@1:CIHM0ogKEICAgIDR_evJAQ%7CCgwI3YbDogYQuKX22QM%7C?hl=en",
                "review_text": "Disappointing. For all of those reviews I was expecting something more. Chipsa was soggy and had faint colour. I had rock as a fish and it wasn't great either, it definitely could be fried a bit less.",
                "review_photos": [],
                "business_response_text": null,
                "review_services": {
                    "Service": "Dine in",
                    "Meal type": "Lunch",
                    "Price per person": "£10–20"
                },
                "translations": {
                    "en": "Disappointing. For all of those reviews I was expecting something more. Chipsa was soggy and had faint colour. I had rock as a fish and it wasn't great either, it definitely could be fried a bit less."
                },
                "review_rate": 2,
                "review_cursor": "CAESY0NBRVFIQnBFUTJwRlNVRlNTWEJEWjI5QlVEY3Rjbmx3VVhCZlgxOWZSV2hDT1ZOR04wTnlURmRGZEhCMlRXVk1RVUZCUVVGQlIyZHVPVE15VVVObFExTkZNazVaV1VGRFNVRQ=="
            },
            {
                "user_name": "david porter",
                "user_total_reviews": 19,
                "user_total_photos": 0,
                "user_avatar": "https://lh3.googleusercontent.com/a-/ALV-UjUB4OGI9n5Mf4lH3SD_qDVDzf7ickpuzcXQ98vtbEreQdRlKlH_=s120-c-rp-mo-ba2-br100",
                "user_link": "https://www.google.com/maps/contrib/113513097221625933372?hl=en",
                "iso_date": "2024-04-03 22:19:49",
                "iso_date_timestamp": 1712182789121463,
                "iso_date_of_last_edit": "2024-04-03 22:19:49",
                "iso_date_of_last_edit_timestamp": 1712182789121463,
                "review_id": "ChZDSUhNMG9nS0VJQ0FnSUNEdjd5UmFREAE",
                "review_time": "a year ago",
                "review_timestamp": 1712182789121463,
                "review_link": "https://www.google.com/maps/reviews/data=!4m8!14m7!1m6!2m5!1sChZDSUhNMG9nS0VJQ0FnSUNEdjd5UmFREAE!2m1!1s0x0:0x92f3b74b723127f1!3m1!1s2@1:CIHM0ogKEICAgICDv7yRaQ%7CCgsIhay3sAYQ2MH1OQ%7C?hl=en",
                "review_text": "Over saturated battered sausage, was binned!\nNo adult staff = disaster in my opinion!\nShame on the owners!\n\nWill NOT RETURN.",
                "review_photos": [],
                "business_response_text": null,
                "review_services": {
                    "Food": 1,
                    "Service": 2,
                    "Atmosphere": 1
                },
                "translations": {
                    "en": "Over saturated battered sausage, was binned!\nNo adult staff = disaster in my opinion!\nShame on the owners!\n\nWill NOT RETURN."
                },
                "review_rate": 2,
                "review_cursor": "CAESY0NBRVFIUnBFUTJwRlNVRlNTWEJEWjI5QlVEY3Rjbmt3UTNSZlgxOWZSV2hFWkd3M1MxSlRXRUV0V2pjMmVFWm9ZMEZCUVVGQlIyZHVPVE00TUVOalZtNTZMVjgwV1VGRFNVRQ=="
            },
            {
                "user_name": "Clint Gregory",
                "user_total_reviews": 21,
                "user_total_photos": 0,
                "user_avatar": "https://lh3.googleusercontent.com/a-/ALV-UjUJO7qiIAdCPjO7Za3zTZGo9yKtwANShZAE3hLaslA2UdEGjgx7=s120-c-rp-mo-ba2-br100",
                "user_link": "https://www.google.com/maps/contrib/117871425037331192342?hl=en",
                "iso_date": "2022-08-11 08:01:36",
                "iso_date_timestamp": 1660204896447867,
                "iso_date_of_last_edit": "2022-08-11 08:01:36",
                "iso_date_of_last_edit_timestamp": 1660204896447867,
                "review_id": "ChdDSUhNMG9nS0VJQ0FnSUR1a0ltNDZ3RRAB",
                "review_time": "3 years ago",
                "review_timestamp": 1660204896447867,
                "review_link": "https://www.google.com/maps/reviews/data=!4m8!14m7!1m6!2m5!1sChdDSUhNMG9nS0VJQ0FnSUR1a0ltNDZ3RRAB!2m1!1s0x0:0x92f3b74b723127f1!3m1!1s2@1:CIHM0ogKEICAgIDukIm46wE%7CCgwI4O7SlwYQ-NDH1QE%7C?hl=en",
                "review_text": "Seemed clean and tidy but I had a poor piece of cod- had a lot of liquid coming from the fish and the batter was hard not crispy\nLooking at the other reviews I may have just been unlucky on a very hot busy day",
                "review_photos": [],
                "business_response_text": null,
                "review_services": {
                    "Service": "Dine in",
                    "Meal type": "Dinner",
                    "Price per person": "£10–20"
                },
                "translations": {
                    "en": "Seemed clean and tidy but I had a poor piece of cod- had a lot of liquid coming from the fish and the batter was hard not crispy\nLooking at the other reviews I may have just been unlucky on a very hot busy day"
                },
                "review_rate": 2,
                "review_cursor": "CAESY0NBRVFIaHBFUTJwRlNVRlNTWEJEWjI5QlVEY3RjbmsxY1VoZlgxOWZSV2hDTTNKNVRXWjRlVk5OWVd0d05tNTZTVUZCUVVGQlIyZHVPVFJCVVVObVdGRlVjakJCV1VGRFNVRQ=="
            },
            {
                "user_name": "Ninja 1400 Gayle",
                "user_total_reviews": 16,
                "user_total_photos": 4,
                "user_avatar": "https://lh3.googleusercontent.com/a/ACg8ocJIwckVwx5uEHaqAjgStDXent32pceL4FZuby_JfaXH1TEUlQ=s120-c-rp-mo-ba2-br100",
                "user_link": "https://www.google.com/maps/contrib/106468410752652973497?hl=en",
                "iso_date": "2017-08-20 17:13:59",
                "iso_date_timestamp": 1503249239483000,
                "iso_date_of_last_edit": "2017-08-20 17:13:59",
                "iso_date_of_last_edit_timestamp": 1503249239483000,
                "review_id": "ChdDSUhNMG9nS0VJQ0FnSURRcUoycG93RRAB",
                "review_time": "8 years ago",
                "review_timestamp": 1503249239483000,
                "review_link": "https://www.google.com/maps/reviews/data=!4m8!14m7!1m6!2m5!1sChdDSUhNMG9nS0VJQ0FnSURRcUoycG93RRAB!2m1!1s0x0:0x92f3b74b723127f1!3m1!1s2@1:CIHM0ogKEICAgIDQqJ2powE%7CCgwI14bnzAUQwP2n5gE%7C?hl=en",
                "review_text": "We found the food hot and fresh though the service could of been a little more welcoming..",
                "review_photos": [],
                "business_response_text": null,
                "review_services": [],
                "translations": {
                    "en": "We found the food hot and fresh though the service could of been a little more welcoming.."
                },
                "review_rate": 2,
                "review_cursor": "CAESY0NBRVFIeHBFUTJwRlNVRlNTWEJEWjI5QlVEY3Rjakp5UlhGMlgxOWZSV2hCY2t4WGFUWTRSbk5RU2xoelZqQXlORUZCUVVGQlIyZHVPVFpVYjBOdlpqbGpPR3RSV1VGRFNVRQ=="
            },
            {
                "user_name": "Val Brown",
                "user_total_reviews": 9,
                "user_total_photos": 0,
                "user_avatar": "https://lh3.googleusercontent.com/a/ACg8ocJlGeNmufSruV6vfA2kboesJ7M-BbOq-4OdA5E6VJV-wJIdiw=s120-c-rp-mo-br100",
                "user_link": "https://www.google.com/maps/contrib/101803567751791493960?hl=en",
                "iso_date": "2019-06-07 08:29:47",
                "iso_date_timestamp": 1559896186513993,
                "iso_date_of_last_edit": "2019-06-07 08:29:47",
                "iso_date_of_last_edit_timestamp": 1559896186513993,
                "review_id": "ChZDSUhNMG9nS0VJQ0FnSUM0Z1pMME5nEAE",
                "review_time": "6 years ago",
                "review_timestamp": 1559896186513993,
                "review_link": "https://www.google.com/maps/reviews/data=!4m8!14m7!1m6!2m5!1sChZDSUhNMG9nS0VJQ0FnSUM0Z1pMME5nEAE!2m1!1s0x0:0x92f3b74b723127f1!3m1!1s2@1:CIHM0ogKEICAgIC4gZL0Ng%7CCgwI-sDo5wUQqNKL9QE%7C?hl=en",
                "review_text": "I asked for a large cod and chips, when I opened the box at home, the cod was certainly was not as large as the last time I used Beach 48.",
                "review_photos": [],
                "business_response_text": "Please contact us at info@beach48.co.uk we will be more than happy to put this right for you",
                "review_services": [],
                "owner_answer": {
                    "date": "6 years ago",
                    "text": {
                        "en": "Please contact us at info@beach48.co.uk we will be more than happy to put this right for you",
                        "": null
                    }
                },
                "translations": {
                    "en": "I asked for a large cod and chips, when I opened the box at home, the cod was certainly was not as large as the last time I used Beach 48."
                },
                "review_rate": 2,
                "review_cursor": "CAESY0NBRVFJQnBFUTJwRlNVRlNTWEJEWjI5QlVEY3Rjako2Um01ZlgxOWZSV2hFV1U0MmNEUTRkRGN4Y0ZjdFJuZEZSVUZCUVVGQlIyZHVPVFpaWjBOc1RUZDRTVmMwV1VGRFNVRQ=="
            },
            {
                "user_name": "William Peel",
                "user_total_reviews": 108,
                "user_total_photos": 91,
                "user_avatar": "https://lh3.googleusercontent.com/a/ACg8ocKRrqESqirVb6bVu35k9zaK80sjIf1csikQ24bdEgfNUGQjaA=s120-c-rp-mo-ba5-br100",
                "user_link": "https://www.google.com/maps/contrib/112038860151742752324?hl=en",
                "iso_date": "2023-06-23 13:20:17",
                "iso_date_timestamp": 1687526416773598,
                "iso_date_of_last_edit": "2023-06-23 13:20:17",
                "iso_date_of_last_edit_timestamp": 1687526416773598,
                "review_id": "ChZDSUhNMG9nS0VJQ0FnSUNKd3FqTUl3EAE",
                "review_time": "2 years ago",
                "review_timestamp": 1687526416773598,
                "review_link": "https://www.google.com/maps/reviews/data=!4m8!14m7!1m6!2m5!1sChZDSUhNMG9nS0VJQ0FnSUNKd3FqTUl3EAE!2m1!1s0x0:0x92f3b74b723127f1!3m1!1s2@1:CIHM0ogKEICAgICJwqjMIw%7CCgwIkLjWpAYQsNbw8AI%7C?hl=en",
                "review_text": "Very poor cod and soggy chips.",
                "review_photos": [],
                "business_response_text": null,
                "review_services": {
                    "Service": 4,
                    "Meal type": "Dinner",
                    "Price per person": "£20–30",
                    "Food": 2
                },
                "translations": {
                    "en": "Very poor cod and soggy chips."
                },
                "review_rate": 2,
                "review_cursor": "CAESY0NBRVFJUnBFUTJwRlNVRlNTWEJEWjI5QlVEY3RjalpUTkdWUVgxOWZSV2hCU1hGeFRFNXFNRTF2ZEVNdFowTXRXVUZCUVVGQlIyZHVPVGhvUlVOa2VHVlhXRzV2V1VGRFNVRQ=="
            },
            {
                "user_name": "Robert Cormack",
                "user_total_reviews": 3,
                "user_total_photos": 0,
                "user_avatar": "https://lh3.googleusercontent.com/a/ACg8ocJZWA33VNSQWXDIeVeF0jI3WhFtKwfVJnOJ32Yr6bqpTwmhxA=s120-c-rp-mo-br100",
                "user_link": "https://www.google.com/maps/contrib/115387468522614917905?hl=en",
                "iso_date": "2018-06-10 22:30:03",
                "iso_date_timestamp": 1528669803497000,
                "iso_date_of_last_edit": "2018-06-10 22:30:03",
                "iso_date_of_last_edit_timestamp": 1528669803497000,
                "review_id": "ChZDSUhNMG9nS0VJQ0FnSUN3NEthQ1ZnEAE",
                "review_time": "7 years ago",
                "review_timestamp": 1528669803497000,
                "review_link": "https://www.google.com/maps/reviews/data=!4m8!14m7!1m6!2m5!1sChZDSUhNMG9nS0VJQ0FnSUN3NEthQ1ZnEAE!2m1!1s0x0:0x92f3b74b723127f1!3m1!1s2@1:CIHM0ogKEICAgICw4KaCVg%7CCgwI68z22AUQwLz-7AE%7C?hl=en",
                "review_text": null,
                "review_photos": [],
                "business_response_text": null,
                "review_services": [],
                "translations": [],
                "review_rate": 2,
                "review_cursor": "CAESYENBRVFJaHBDUTJrNFNVRlNTVzVEWjI5QlVEY3RkV1pmWDE5ZlgxOWZSV2hDTm1aRk0yczVUMDFzU0dnNFZsSlpXVUZCUVVGQlIyZG1YMEZ3ZDFWTVpYZFhSMEZCYVVGQg=="
            },
            {
                "user_name": "Alan Darbyshire",
                "user_total_reviews": 55,
                "user_total_photos": 72,
                "user_avatar": "https://lh3.googleusercontent.com/a-/ALV-UjU4x-2m8hZbKkWE6TEaTN-AUMrP3XOLrKeL9nDBsG8o_DFZ44w=s120-c-rp-mo-ba3-br100",
                "user_link": "https://www.google.com/maps/contrib/115142051993819984472?hl=en",
                "iso_date": "2023-09-21 17:00:22",
                "iso_date_timestamp": 1695315622440424,
                "iso_date_of_last_edit": "2023-09-21 17:00:22",
                "iso_date_of_last_edit_timestamp": 1695315622440424,
                "review_id": "ChdDSUhNMG9nS0VJQ0FnSUNaXzVPLTVRRRAB",
                "review_time": "2 years ago",
                "review_timestamp": 1695315622440424,
                "review_link": "https://www.google.com/maps/reviews/data=!4m8!14m7!1m6!2m5!1sChdDSUhNMG9nS0VJQ0FnSUNaXzVPLTVRRRAB!2m1!1s0x0:0x92f3b74b723127f1!3m1!1s2@1:CIHM0ogKEICAgICZ_5O-5QE%7CCgwIpu2xqAYQwKyB0gE%7C?hl=en",
                "review_text": "Todays (Thursday 21st) chips for some reason absolutely disgusting, not sure what’s happened just in edible. fish as always just brilliant.",
                "review_photos": [
                    "https://lh3.googleusercontent.com/geougc-cs/AMBA38soOaTlmfAqOy1IgNIw2TWIoMUc1xNlB8tdNlPtzmBDOj24VChphKhncFntsI_tm0uTz9Nev8putTIUQuMzDCClmJ41S2dwhns7hCch_8NaG4wCbMTfZHyrvCWH30hWuw9p344C"
                ],
                "business_response_text": "Alan, We are very sorry that you were disappointed with you chips, we had a different variety of potato delivered by our supplier this week, we have taken on board feedback. Please get in touch and we will happily refund your meals for you either pop back into the takeaway or call us 01303874848 to arrange your refund.",
                "review_services": {
                    "Service": 3,
                    "Food": 1,
                    "Atmosphere": 3
                },
                "owner_answer": {
                    "date": "2 years ago",
                    "text": {
                        "en": "Alan, We are very sorry that you were disappointed with you chips, we had a different variety of potato delivered by our supplier this week, we have taken on board feedback. Please get in touch and we will happily refund your meals for you either pop back into the takeaway or call us 01303874848 to arrange your refund.",
                        "": null
                    }
                },
                "translations": {
                    "en": "Todays (Thursday 21st) chips for some reason absolutely disgusting, not sure what’s happened just in edible. fish as always just brilliant."
                },
                "review_rate": 3,
                "review_cursor": "CAESY0NBRVFJeHBFUTJwRlNVRlNTWEJEWjI5QlVEY3RlR2R4UjFSbVgxOWZSV2hFVmxwTGVtOWFhMVY2TFRkUlNERnRTVUZCUVVGQlIyZHVPVEppTUVOa1ZXUlJhR1JqV1VGRFNVRQ=="
            },
            {
                "user_name": "Beverley",
                "user_total_reviews": 10,
                "user_total_photos": 3,
                "user_avatar": "https://lh3.googleusercontent.com/a/ACg8ocKQUp19IhhKPJrO5LrbnXe16jXhbjZ5Skd5bpUIHQb79i25xNk=s120-c-rp-mo-br100",
                "user_link": "https://www.google.com/maps/contrib/113265586135669988403?hl=en",
                "iso_date": "2025-05-31 18:01:04",
                "iso_date_timestamp": 1748714464302602,
                "iso_date_of_last_edit": "2025-05-31 18:01:04",
                "iso_date_of_last_edit_timestamp": 1748714464302602,
                "review_id": "ChdDSUhNMG9nS0VLU1lzdVd1Z1pEejhRRRAB",
                "review_time": "5 months ago",
                "review_timestamp": 1748714464302602,
                "review_link": "https://www.google.com/maps/reviews/data=!4m8!14m7!1m6!2m5!1sChdDSUhNMG9nS0VLU1lzdVd1Z1pEejhRRRAB!2m1!1s0x0:0x92f3b74b723127f1!3m1!1s2@1:CIHM0ogKEKSYsuWugZDz8QE%7CCgwI4IftwQYQkK6lkAE%7C?hl=en",
                "review_text": "Disappointed as cafe shuts at 6\nOnly takeaway available\nNormally tasty food freshly cooked and good service…. Maybe change of hand but  whatever the reason open time needs to be clarified",
                "review_photos": [],
                "business_response_text": null,
                "review_services": {
                    "Service": "Dine in"
                },
                "translations": {
                    "en": "Disappointed as cafe shuts at 6\nOnly takeaway available\nNormally tasty food freshly cooked and good service…. Maybe change of hand but  whatever the reason open time needs to be clarified"
                },
                "review_rate": 3,
                "review_cursor": "CAESY0NBRVFKQnBFUTJwRlNVRlNTWEJEWjI5QlVEY3RlR2MwYmxsbVgxOWZSV2hEYUV4NFNHWlVSSFJZU0d0UU9XZEZORUZCUVVGQlIyZHVPVEpuVFVOaFRtZ3RNamxGV1VGRFNVRQ=="
            },
            {
                "user_name": "Scott Gunner",
                "user_total_reviews": 11,
                "user_total_photos": 0,
                "user_avatar": "https://lh3.googleusercontent.com/a/ACg8ocIOOwd5pTg9PdcuDVy__m1TD_9fZoT1pdVa93WgJiCW8pFSjw=s120-c-rp-mo-br100",
                "user_link": "https://www.google.com/maps/contrib/110326924311050120477?hl=en",
                "iso_date": "2025-02-11 17:49:35",
                "iso_date_timestamp": 1739296175362229,
                "iso_date_of_last_edit": "2025-02-11 17:54:49",
                "iso_date_of_last_edit_timestamp": 1739296489418606,
                "review_id": "ChZDSUhNMG9nS0VJQ0FnTURBczlxYUNnEAE",
                "review_time": "8 months ago",
                "review_timestamp": 1739296489418606,
                "review_link": "https://www.google.com/maps/reviews/data=!4m8!14m7!1m6!2m5!1sChZDSUhNMG9nS0VJQ0FnTURBczlxYUNnEAE!2m1!1s0x0:0x92f3b74b723127f1!3m1!1s2@1:CIHM0ogKEICAgMDAs9qaCg%7CCgwI6Z2uvQYQsNfNxwE%7C?hl=en",
                "review_text": "Have used these for years. But today the sausage in batter was swimming in grease to the point it ran like water. Chips overcooked and clearly been cooked hours earlier. Totally soggy and dark brown. Such a shame",
                "review_photos": [],
                "business_response_text": null,
                "review_services": [],
                "translations": {
                    "en": "Have used these for years. But today the sausage in batter was swimming in grease to the point it ran like water. Chips overcooked and clearly been cooked hours earlier. Totally soggy and dark brown. Such a shame"
                },
                "review_rate": 3,
                "review_cursor": "CAESY0NBRVFKUnBFUTJwRlNVRlNTWEJEWjI5QlVEY3RlR2huTmxCbVgxOWZSV2hCTFRGbVRuSjBkRTVUY1ZOSlFuTjViMEZCUVVGQlIyZHVPVEp6WjBOaGQyNWFkMFJWV1VGRFNVRQ=="
            },
            {
                "user_name": "Tony Adams",
                "user_total_reviews": 141,
                "user_total_photos": 69,
                "user_avatar": "https://lh3.googleusercontent.com/a/ACg8ocJu4HCKXGcj-_yyMjyUlNwTrQMttIfg_Q_Dhb0NinjNlw-hgQ=s120-c-rp-mo-ba5-br100",
                "user_link": "https://www.google.com/maps/contrib/109024957215535459862?hl=en",
                "iso_date": "2021-08-24 18:15:34",
                "iso_date_timestamp": 1629828933555313,
                "iso_date_of_last_edit": "2021-08-24 18:16:37",
                "iso_date_of_last_edit_timestamp": 1629828997404060,
                "review_id": "ChZDSUhNMG9nS0VJQ0FnSURhcmFhS0d3EAE",
                "review_time": "4 years ago",
                "review_timestamp": 1629828997404060,
                "review_link": "https://www.google.com/maps/reviews/data=!4m8!14m7!1m6!2m5!1sChZDSUhNMG9nS0VJQ0FnSURhcmFhS0d3EAE!2m1!1s0x0:0x92f3b74b723127f1!3m1!1s2@1:CIHM0ogKEICAgIDaraaKGw%7CCgwIhe-UiQYQ4O7VwAE%7C?hl=en",
                "review_text": "Very popular eat in and take away fish bar. We eat in. VERY clean and feels safe. Fish (all 4 of us had cod) was excellent; Not so keen on the chips! Reasonably priced generous portions and friendly, helpful staff",
                "review_photos": [],
                "business_response_text": null,
                "review_services": [],
                "translations": {
                    "en": "Very popular eat in and take away fish bar. We eat in. VERY clean and feels safe. Fish (all 4 of us had cod) was excellent; Not so keen on the chips! Reasonably priced generous portions and friendly, helpful staff"
                },
                "review_rate": 3,
                "review_cursor": "CAESY0NBRVFKaHBFUTJwRlNVRlNTWEJEWjI5QlVEY3RlR3BPVVdsZlgxOWZSV2hEWVRkT1NEVmxWVlJaZEhNMFEzZDNjMEZCUVVGQlIyZHVPVE5PYTBOb1NXRm1TSFZOV1VGRFNVRQ=="
            },
            {
                "user_name": "Ria FirstLadiesUK",
                "user_total_reviews": 11,
                "user_total_photos": 15,
                "user_avatar": "https://lh3.googleusercontent.com/a-/ALV-UjUzs5g-1LOqKwKguFyy4gWE4T1SbI3AiwSJ860Osx-vTfewfW6H=s120-c-rp-mo-ba2-br100",
                "user_link": "https://www.google.com/maps/contrib/115383070880036111420?hl=en",
                "iso_date": "2024-07-07 09:22:11",
                "iso_date_timestamp": 1720344131384755,
                "iso_date_of_last_edit": "2024-07-07 09:22:11",
                "iso_date_of_last_edit_timestamp": 1720344131384755,
                "review_id": "ChdDSUhNMG9nS0VJQ0FnSUNycnZYWmdBRRAB",
                "review_time": "a year ago",
                "review_timestamp": 1720344131384755,
                "review_link": "https://www.google.com/maps/reviews/data=!4m8!14m7!1m6!2m5!1sChdDSUhNMG9nS0VJQ0FnSUNycnZYWmdBRRAB!2m1!1s0x0:0x92f3b74b723127f1!3m1!1s2@1:CIHM0ogKEICAgICrrvXZgAE%7CCgwIw7yptAYQuMq7twE%7C?hl=en",
                "review_text": "I brought fish and chips last weekend the Que when I got to the beach was so long decided on leaving I would have to try, waited around 30 mins for the food staff was pleasant and food was lovely would say 6/10",
                "review_photos": [],
                "business_response_text": null,
                "review_services": {
                    "Service": 3,
                    "Meal type": "Dinner",
                    "Price per person": "£10–20",
                    "Food": 3,
                    "Atmosphere": 3,
                    "Recommended dishes": "Fish & Chips, Large Chips, Jumbo Sausage"
                },
                "translations": {
                    "en": "I brought fish and chips last weekend the Que when I got to the beach was so long decided on leaving I would have to try, waited around 30 mins for the food staff was pleasant and food was lovely would say 6/10"
                },
                "review_rate": 3,
                "review_cursor": "CAESY0NBRVFKeHBFUTJwRlNVRlNTWEJEWjI5QlVEY3RlR3BRYlVObVgxOWZSV2hDVGtkeGNVOUhTRUl6Y1VwVFoyazFaMEZCUVVGQlIyZHVPVE5QVlVOaU0wNWZlVTFqV1VGRFNVRQ=="
            },
            {
                "user_name": "Lisa Sargent",
                "user_total_reviews": 53,
                "user_total_photos": 29,
                "user_avatar": "https://lh3.googleusercontent.com/a-/ALV-UjUEA-h6hlyVc97OfWyRG8mTR2081QFfJQXxI2FRr0QjEkDaL64=s120-c-rp-mo-ba3-br100",
                "user_link": "https://www.google.com/maps/contrib/110398382471743694406?hl=en",
                "iso_date": "2024-09-05 19:41:40",
                "iso_date_timestamp": 1725565299599451,
                "iso_date_of_last_edit": "2024-09-05 19:41:40",
                "iso_date_of_last_edit_timestamp": 1725565299599451,
                "review_id": "ChdDSUhNMG9nS0VJQ0FnSUNINFpLRDFnRRAB",
                "review_time": "a year ago",
                "review_timestamp": 1725565299599451,
                "review_link": "https://www.google.com/maps/reviews/data=!4m8!14m7!1m6!2m5!1sChdDSUhNMG9nS0VJQ0FnSUNINFpLRDFnRRAB!2m1!1s0x0:0x92f3b74b723127f1!3m1!1s2@1:CIHM0ogKEICAgICH4ZKD1gE%7CCgwI85LotgYQ-MrrnQI%7C?hl=en",
                "review_text": "I don't know if I am allergic to fish, but I was on the coach trip today and coming home, I felt very sick and sore throat and hard to swallow now. I'll leave it till tomorrow but I don't feel well.",
                "review_photos": [],
                "business_response_text": null,
                "review_services": {
                    "Service": 5,
                    "Meal type": "Lunch",
                    "Price per person": "£10–20",
                    "Food": 2,
                    "Atmosphere": 4,
                    "Recommended dishes": "Large Cod and Chips"
                },
                "translations": {
                    "en": "I don't know if I am allergic to fish, but I was on the coach trip today and coming home, I felt very sick and sore throat and hard to swallow now. I'll leave it till tomorrow but I don't feel well."
                },
                "review_rate": 3,
                "review_cursor": "CAESY0NBRVFLQnBFUTJwRlNVRlNTWEJEWjI5QlVEY3RlR3B4TWtWZlgxOWZSV2hEYkRscFFqSlpTVU5FUVRGSlJqUlFNRUZCUVVGQlIyZHVPVE5YYjBOaWFuaE1Sa2hCV1VGRFNVRQ=="
            }
        ]
    }
}